LICENSE
MANIFEST.in
README.rst
setup.py
hypothesis_gufunc/__init__.py
hypothesis_gufunc/gufunc.py
hypothesis_gufunc.egg-info/PKG-INFO
hypothesis_gufunc.egg-info/SOURCES.txt
hypothesis_gufunc.egg-info/dependency_links.txt
hypothesis_gufunc.egg-info/requires.txt
hypothesis_gufunc.egg-info/top_level.txt
hypothesis_gufunc/extra/__init__.py
hypothesis_gufunc/extra/xr.py
requirements/base.in
requirements/extra.in