Metadata-Version: 2.1
Name: hypothesis-gufunc
Version: 0.0.5
Summary: Extension to hypothesis to generate inputs for general universal (GU) numpy functions.
Home-page: https://github.com/uber/hypothesis-gufunc
Author: Ryan Turner
Author-email: rdturnermtl@github.com
License: Apache v2
Project-URL: Documentation, https://hypothesis-gufunc.readthedocs.io
Platform: any
Classifier: Framework :: Hypothesis
Classifier: Framework :: Pytest
Classifier: Intended Audience :: Developers
Classifier: Operating System :: Unix
Classifier: Operating System :: POSIX
Classifier: Programming Language :: Python
Classifier: Programming Language :: Python :: 3
Classifier: Programming Language :: Python :: 3.6
Classifier: Topic :: Software Development :: Testing
Provides-Extra: xarray
